{
	"name": "AudioFN",
	"events": [
		{
			"functionName": "playSfx",
			"functionDescription": "",
			"functionCategory": "",
			"functionReturnType": "none",
			"functionCopyPicked": false,
			"functionIsAsync": false,
			"functionParameters": [
				{
					"name": "sfx",
					"type": "number",
					"initialValue": "0",
					"comment": "",
					"sid": 171353297228843
				}
			],
			"eventType": "function-block",
			"conditions": [],
			"actions": [],
			"sid": 791313254967215,
			"children": [
				{
					"eventType": "block",
					"conditions": [
						{
							"id": "compare-eventvar",
							"objectClass": "System",
							"sid": 138719643867348,
							"parameters": {
								"variable": "sfx",
								"comparison": 0,
								"value": "0"
							}
						}
					],
					"actions": [
						{
							"id": "play",
							"objectClass": "Audio",
							"sid": 331698521022516,
							"parameters": {
								"audio-file": "SwordSwish01",
								"loop": "not-looping",
								"volume": "0",
								"stereo-pan": "0",
								"tag-optional": "\"\""
							}
						}
					],
					"sid": 753677701499571
				},
				{
					"eventType": "block",
					"conditions": [
						{
							"id": "compare-eventvar",
							"objectClass": "System",
							"sid": 517526168230867,
							"parameters": {
								"variable": "sfx",
								"comparison": 0,
								"value": "1"
							}
						}
					],
					"actions": [
						{
							"id": "play",
							"objectClass": "Audio",
							"sid": 211867208556925,
							"parameters": {
								"audio-file": "GemPickUp01",
								"loop": "not-looping",
								"volume": "0",
								"stereo-pan": "0",
								"tag-optional": "\"\""
							}
						}
					],
					"sid": 468926283502199
				},
				{
					"eventType": "block",
					"conditions": [
						{
							"id": "compare-eventvar",
							"objectClass": "System",
							"sid": 303959433368652,
							"parameters": {
								"variable": "sfx",
								"comparison": 0,
								"value": "2"
							}
						}
					],
					"actions": [
						{
							"id": "play",
							"objectClass": "Audio",
							"sid": 173067798364570,
							"parameters": {
								"audio-file": "DestroyPot01",
								"loop": "not-looping",
								"volume": "0",
								"stereo-pan": "0",
								"tag-optional": "\"\""
							}
						}
					],
					"sid": 757302287999720
				}
			]
		}
	],
	"sid": 474515870482890
}